nv2apretty/__about__.py
nv2apretty/__init__.py
nv2apretty/pixel_shader_definition.py
nv2apretty/prettify.py
nv2apretty/pvideo.py
nv2apretty/extracted_data/__init__.py
nv2apretty/subprocessors/__init__.py
nv2apretty/subprocessors/color_combiner.py
nv2apretty/subprocessors/common_shader_state.py
nv2apretty/subprocessors/fixed_function_shader.py
nv2apretty/subprocessors/frame_summary.py
nv2apretty/subprocessors/pipeline_state.py
nv2a_pretty-0.2.4.dist-info/METADATA
nv2a_pretty-0.2.4.dist-info/WHEEL
nv2a_pretty-0.2.4.dist-info/entry_points.txt
nv2a_pretty-0.2.4.dist-info/licenses/LICENSE
nv2a_pretty-0.2.4.dist-info/RECORD
