Metadata-Version: 2.4
Name: nv2a-pretty
Version: 0.2.4
Summary: Visualizer for xemu/nv2a-trace XBOX GPU (nv2a) logs.
Project-URL: Documentation, https://github.com/abaire/nv2apretty#readme
Project-URL: Issues, https://github.com/abaire/nv2apretty/issues
Project-URL: Source, https://github.com/abaire/nv2apretty
Author-email: Erik Abair <erik.abair@bearbrains.work>
License: This is free and unencumbered software released into the public domain.
License-File: LICENSE
Keywords: nv2a,nvidia,xbox,xemu
Classifier: Development Status :: 3 - Alpha
Classifier: Environment :: Console
Classifier: Intended Audience :: Developers
Classifier: Operating System :: OS Independent
Classifier: Programming Language :: Python
Classifier: Programming Language :: Python :: 3.10
Classifier: Programming Language :: Python :: 3.11
Classifier: Programming Language :: Python :: 3.12
Classifier: Topic :: Software Development :: Documentation
Requires-Python: >=3.10
Requires-Dist: nv2a-vsh>=0.1.7
